APIFuzzer-0.9.13.data/scripts/APIFuzzer
apifuzzer/__init__.py
apifuzzer/apifuzzerreport.py
apifuzzer/base_template.py
apifuzzer/custom_fuzzers.py
apifuzzer/exceptions.py
apifuzzer/fuzz_model.py
apifuzzer/fuzz_utils.py
apifuzzer/fuzzer.py
apifuzzer/move_json_parts.py
apifuzzer/openapi_template_generator.py
apifuzzer/server_fuzzer.py
apifuzzer/template_generator_base.py
apifuzzer/utils.py
apifuzzer/version.py
apifuzzer/fuzzer_target/fuzz_request_sender.py
apifuzzer/fuzzer_target/request_base_functions.py
APIFuzzer-0.9.13.dist-info/LICENSE
APIFuzzer-0.9.13.dist-info/METADATA
APIFuzzer-0.9.13.dist-info/WHEEL
APIFuzzer-0.9.13.dist-info/top_level.txt
APIFuzzer-0.9.13.dist-info/RECORD
