Metadata-Version: 2.1
Name: APIFuzzer
Version: 0.9.13
Summary: Fuzz test your application using Swagger or OpenAPI definition without coding
Home-page: https://github.com/KissPeter/APIFuzzer/
Author: Peter Kiss
Author-email: peter.kiss@linuxadm.hu
License: GNU General Public License v3.0
Keywords: Fuzz test,QA,Software Quality Assurance,Security testing,Swagger,OpenAPI
Platform: UNKNOWN
Classifier: Development Status :: 4 - Beta
Classifier: Intended Audience :: Developers
Classifier: Topic :: Software Development :: Quality Assurance
Classifier: Topic :: Software Development :: Testing
Classifier: Natural Language :: English
Classifier: License :: OSI Approved :: GNU General Public License v3 (GPLv3)
Classifier: Programming Language :: Python :: 3.6
Classifier: Programming Language :: Python :: 3.7
Classifier: Programming Language :: Python :: 3.8
Classifier: Programming Language :: Python :: 3.9
Requires-Python: >=3.6, <4
License-File: LICENSE
Requires-Dist: kittyfuzzer (==0.7.4)
Requires-Dist: pycurl (==7.43.0.6)
Requires-Dist: ruamel.yaml (==0.16.12)
Requires-Dist: junit-xml (==1.9)
Requires-Dist: jsonpath-ng (==1.5.2)
Requires-Dist: PyYAML (==6.0)
Requires-Dist: json-ref-dict (>=0.7.1)
